apogee/SerialClient.py
apogee/__init__.py
apogee/cli.py
apogee/version.py
apogee/bluetooth/BleClient.py
apogee/bluetooth/BleScanner.py
apogee/bluetooth/Calculators.py
apogee/bluetooth/SensorClasses.py
apogee/bluetooth/__init__.py
apogee/bluetooth/commands.py
apogee/bluetooth/uuids.py
apogee/modbus/ModbusClient.py
apogee/modbus/ModbusSensorRegisterDict.py
apogee/modbus/__init__.py
apogee/modbus/commands.py
apogee/sdi12/SDI12Client.py
apogee/sdi12/__init__.py
apogee/tools/MessageHandler.py
apogee/tools/__init__.py
apogee/usb/__init__.py
apogee_sdk-0.0.4.dist-info/licenses/LICENSE
apogee_sdk-0.0.4.dist-info/METADATA
apogee_sdk-0.0.4.dist-info/WHEEL
apogee_sdk-0.0.4.dist-info/entry_points.txt
apogee_sdk-0.0.4.dist-info/top_level.txt
apogee_sdk-0.0.4.dist-info/RECORD
