Metadata-Version: 2.4
Name: apogee-sdk
Version: 0.0.4
Summary: Interface with Apogee sensors
Author-email: "Apogee Instruments, Inc." <developer@apogeeinstruments.com>
License: MIT License
Classifier: Development Status :: 5 - Production/Stable
Classifier: Intended Audience :: Science/Research
Classifier: Programming Language :: Python :: 3
Classifier: License :: OSI Approved :: MIT License
Classifier: Operating System :: POSIX :: Linux
Classifier: Topic :: Scientific/Engineering
Classifier: Topic :: Scientific/Engineering :: Information Analysis
Requires-Python: >=3.7
License-File: LICENSE
Requires-Dist: pyserial
Requires-Dist: bleak
Requires-Dist: asyncio
Dynamic: license-file
